MANIFEST.in
README.md
requirements.txt
setup.py
lfs_criterion_extra/__init__.py
lfs_criterion_extra/admin.py
lfs_criterion_extra/models.py
lfs_criterion_extra/monkey.py
lfs_criterion_extra/tests.py
lfs_criterion_extra.egg-info/PKG-INFO
lfs_criterion_extra.egg-info/SOURCES.txt
lfs_criterion_extra.egg-info/dependency_links.txt
lfs_criterion_extra.egg-info/not-zip-safe
lfs_criterion_extra.egg-info/requires.txt
lfs_criterion_extra.egg-info/top_level.txt
lfs_criterion_extra/templates/manage/criteria/2selection_operators.html
lfs_criterion_extra/templates/manage/criteria/amount_criterion.html
lfs_criterion_extra/templates/manage/criteria/base_criterion.html
lfs_criterion_extra/templates/manage/criteria/category_criterion.html
lfs_criterion_extra/templates/manage/criteria/combinedlengthandgirth_criterion.html
lfs_criterion_extra/templates/manage/criteria/composition_category_criterion.html
lfs_criterion_extra/templates/manage/criteria/country_criterion.html
lfs_criterion_extra/templates/manage/criteria/discounts_criterion.html
lfs_criterion_extra/templates/manage/criteria/distance_criterion.html
lfs_criterion_extra/templates/manage/criteria/for_sale_criterion.html
lfs_criterion_extra/templates/manage/criteria/full_user_criterion.html
lfs_criterion_extra/templates/manage/criteria/full_user_operators.html
lfs_criterion_extra/templates/manage/criteria/group_criterion.html
lfs_criterion_extra/templates/manage/criteria/height_criterion.html
lfs_criterion_extra/templates/manage/criteria/length_criterion.html
lfs_criterion_extra/templates/manage/criteria/manual_delivery_time_criterion.html
lfs_criterion_extra/templates/manage/criteria/manufacturer_criterion.html
lfs_criterion_extra/templates/manage/criteria/max_weight_criterion.html
lfs_criterion_extra/templates/manage/criteria/operator_choices.html
lfs_criterion_extra/templates/manage/criteria/order_count_criterion.html
lfs_criterion_extra/templates/manage/criteria/order_summ_criterion.html
lfs_criterion_extra/templates/manage/criteria/payment_method_criterion.html
lfs_criterion_extra/templates/manage/criteria/price_criterion.html
lfs_criterion_extra/templates/manage/criteria/product_criterion.html
lfs_criterion_extra/templates/manage/criteria/product_price_criterion.html
