Metadata-Version: 1.0
Name: lfs-criterion-extra
Version: 0.1.9
Summary: Extra critetions for LFS
Home-page: http://github.com/suvit/lfs-criterion-extra
Author: Victor Safronovich
Author-email: vsafronovich@gmail.com
License: MIT
Platform: UNKNOWN
